{
	"lc": {
		"name": "Standard Little Cup",
		"format": "gen8lc",
		"type": "2 elimination",
		"rules": {
			"bannedPokemon": [
				"corsola-galar", "cutiefly", "drifloon", "gastly", "gothita", "rufflet", "scyther", "sneasel", "swirlix", "tangela", "vulpix-alola"
			],
			"bannedAbilities": [
				"chlorophyll", "moody"
			],
			"bannedMoves": [
				"baton pass"
			],
			"useAsRule": false
		},
		"sampleTeams": [
			"https://pokepast.es/77b3923c73c320b6/json",
			"https://pokepast.es/7addbd2d6561735e/json",
			"https://pokepast.es/929aa99ae70a25b9/json",
			"https://pokepast.es/6a00cc4daf269138/json",
			"https://pokepast.es/ed3e8de62a9a095e/json",
			"https://pokepast.es/295a88badd10d41f/json",
			"https://pokepast.es/dc70014135bbe423/json",
			"https://pokepast.es/ae2b27c88039a2b2/json",
			"https://pokepast.es/b23382a22b17cd2f/json",
			"https://pokepast.es/90c08a661574c8a7/json",
			"https://pokepast.es/f575996f8ba909e8/json",
			"https://pokepast.es/c28c65c1539b8178/json",
			"https://pokepast.es/3d475983c9138bd8/json",
			"https://pokepast.es/e1269f12db11b080/json",
			"https://pokepast.es/6d2ebc8f178dd7bf/json",
			"https://pokepast.es/4f4634658a15ab1c/json",
			"https://pokepast.es/4654c17bd0a687c7/json",
			"https://pokepast.es/78826c184c786183/json"
		],
		"resources": []
	},
	"lcuu": {
		"name": "Standard Little Cup UnderUsed",
		"about": "LC UU is the tier below LC; any Pokemon that sees under 4.52% usage on the LC ladder (using the weighted 1630 stats) are banned.",
		"format": "gen8lc",
		"type": "1 elimination",
		"rules": {
			"inheritBans": [
				"lc"
			],
			"bannedPokemon": [
				"scraggy", "shellder", "grookey", "scorbunny", "carvanha", "foongus", "magnemite", "mienfoo", "porygon", "abra", "chinchou", "dewpider", "diglett-base", "drilbur", "farfetchd-galar", "ferroseed", "koffing", "mareanie", "mudbray", "munchlax", "onix", "pawniard", "ponyta-base", "spritzee", "timburr", "trapinch", "vullaby", "wingull", "dwebble", "vulpix", "omanyte", "elekid", "magby", "treecko", "swablu", "tirtouga", "archen", "tyrunt", "amaura"
			],
			"useAsRule": true
		},
		"sampleTeams": [
			"https://pokepast.es/50e70f68ce7db506/json",
			"https://pokepast.es/cd231148bdc63291/json",
			"https://pokepast.es/4ef82345a55516bd/json",
			"https://pokepast.es/c063b6bea3007b0a/json"
		],
		"resources": [
			{
				"name": "Main Thread",
				"url": "https://www.smogon.com/forums/threads/swsh-lcuu-metagame-discussion-thread.3660866"
			},
			{
				"name": "Role Compendium",
				"url": "https://www.smogon.com/forums/threads/swsh-lcuu-metagame-discussion-thread.3660866/#post-8385118"
			},
			{
				"name": "Viability Rankings",
				"url": "https://www.smogon.com/forums/threads/swsh-lcuu-metagame-discussion-thread.3660866/#post-8384271"
			}
		]
	},
	"lcubers": {
		"name": "Standard Little Cup Ubers",
		"about": "LC Ubers removes the banlist, so everything and anything is fair game! Warning: do not expect this format to be balanced!",
		"format": "gen8lc",
		"type": "2 elimination",
		"rules": {
			"inheritBansAsUnbans": [
				"lc"
			]
		},
		"sampleTeams": [],
		"resources": []
	},
	"usumlc": {
		"name": "Standard Little Cup (Gen 7)",
		"format": "gen7lc",
		"type": "2 elimination",
		"rules": {
			"bannedPokemon": [
				"aipom", "cutiefly", "drifloon", "gligar", "gothita", "meditite", "misdreavus", "murkrow", "porygon", "scyther", "sneasel", "swirlix", "tangela", "trapinch", "vulpix-base", "wingull", "yanma"
			],
			"bannedItems": [
				"eevium z"
			],
			"bannedMoves": [
				"baton pass", "dragon rage", "sonic boom"
			],
			"useAsRule": false
		},
		"sampleTeams": [
			"https://pokepast.es/8f224d14bf08ea25/json",
			"https://pokepast.es/2f52c88110195146/json",
			"https://pokepast.es/2e808baa0dbcbef3/json",
			"https://pokepast.es/78092b10a29de52a/json",
			"https://pokepast.es/b6883976f26744d8/json",
			"https://pokepast.es/2479a37c805f3aba/json",
			"https://pokepast.es/22b4d75a069eee26/json"
		],
		"resources": []
	},
	"oraslc": {
		"name": "Standard Little Cup (Gen 6)",
		"format": "gen6lc",
		"type": "2 elimination",
		"rules": {
			"bannedPokemon": [
				"drifloon", "gligar", "meditite", "misdreavus", "murkrow", "scyther", "sneasel", "swirlix", "tangela", "yanma"
			],
			"bannedMoves": [
				"baton pass", "dragon rage", "sonic boom", "swagger"
			],
			"useAsRule": false
		},
		"sampleTeams": [
			"https://pokepast.es/ab3d0d6b70fa13e1/json",
			"https://pokepast.es/54395c0d2b8c8202/json",
			"https://pokepast.es/a54325e42d3a938c/json"
		],
		"resources": []
	},
	"bw2lc": {
		"name": "Standard Little Cup (Gen 5)",
		"format": "gen5lc",
		"type": "2 elimination",
		"rules": {
			"bannedPokemon": [
				"gligar", "meditite", "misdreavus", "murkrow", "scraggy", "scyther", "sneasel", "tangela", "vulpix", "yanma"
			],
			"bannedAbilities": [
				"sand rush"
			],
			"bannedItems": [
				"berry juice", "soul dew"
			],
			"bannedMoves": [
				"baton pass", "dragon rage", "sonic boom", "swagger"
			],
			"useAsRule": false
		},
		"sampleTeams": [],
		"resources": []
	},
	"dpplc": {
		"name": "Standard Little Cup (Gen 4)",
		"format": "gen4lc",
		"type": "2 elimination",
		"rules": {
			"bannedPokemon": [
				"meditite", "misdreavus", "murkrow", "scyther", "sneasel", "tangela", "yanma"
			],
			"bannedItems": [
				"berry juice", "deep sea tooth"
			],
			"bannedMoves": [
				"dragon rage", "sonic boom"
			],
			"useAsRule": false
		},
		"sampleTeams": [
			"https://pokepast.es/587bb5ee150c11c0/json",
			"https://pokepast.es/235d193b1488dc94/json"
		],
		"resources": []
	}
}
